bnf.py
ebnf.py
bnf-1.0.5.dist-info/licenses/LICENSE
bnf-1.0.5.dist-info/METADATA
bnf-1.0.5.dist-info/WHEEL
bnf-1.0.5.dist-info/top_level.txt
bnf-1.0.5.dist-info/RECORD
